{
  "version": "1.0.0",
  "description": "Quick reference for quantum computing essentials",
  "sections": {
    "gates": {
      "title": "Common Quantum Gates",
      "groups": [
        {
          "id": "single_qubit",
          "title": "Single-Qubit Gates",
          "color": "#6366F1",
          "items": [
            {"name": "X (NOT)", "matrix": "[[0,1],[1,0]]", "action": "|0⟩↔|1⟩"},
            {"name": "Y", "matrix": "[[0,-i],[i,0]]", "action": "Bit+phase flip"},
            {"name": "Z", "matrix": "[[1,0],[0,-1]]", "action": "|1⟩→-|1⟩"},
            {"name": "H", "matrix": "(1/√2)[[1,1],[1,-1]]", "action": "|0⟩→|+⟩, |1⟩→|-⟩"},
            {"name": "S", "matrix": "[[1,0],[0,i]]", "action": "π/2 phase"},
            {"name": "T", "matrix": "[[1,0],[0,e^(iπ/4)]]", "action": "π/4 phase"}
          ]
        },
        {
          "id": "two_qubit",
          "title": "Two-Qubit Gates",
          "color": "#EC4899",
          "items": [
            {"name": "CNOT/CX", "action": "Flip target if control=|1⟩"},
            {"name": "CZ", "action": "Phase flip if both |1⟩"},
            {"name": "SWAP", "action": "Exchange two qubits"},
            {"name": "iSWAP", "action": "SWAP with phase"}
          ]
        },
        {
          "id": "three_qubit",
          "title": "Three-Qubit Gates",
          "color": "#F59E0B",
          "items": [
            {"name": "Toffoli/CCX", "action": "Flip target if both controls=|1⟩"},
            {"name": "Fredkin/CSWAP", "action": "SWAP if control=|1⟩"}
          ]
        }
      ]
    },
    "states": {
      "title": "Important Quantum States",
      "groups": [
        {
          "id": "single_qubit_states",
          "title": "Single-Qubit States",
          "color": "#8B5CF6",
          "states": [
            {"name": "|0⟩", "vector": "[1,0]", "bloch": "North pole"},
            {"name": "|1⟩", "vector": "[0,1]", "bloch": "South pole"},
            {"name": "|+⟩", "vector": "[1,1]/√2", "bloch": "+X"},
            {"name": "|-⟩", "vector": "[1,-1]/√2", "bloch": "-X"},
            {"name": "|i⟩", "vector": "[1,i]/√2", "bloch": "+Y"},
            {"name": "|-i⟩", "vector": "[1,-i]/√2", "bloch": "-Y"}
          ]
        },
        {
          "id": "bell_states",
          "title": "Bell States",
          "color": "#14B8A6",
          "states": [
            {"name": "|Φ⁺⟩", "expansion": "(|00⟩+|11⟩)/√2", "correlation": "Same"},
            {"name": "|Φ⁻⟩", "expansion": "(|00⟩-|11⟩)/√2", "correlation": "Same"},
            {"name": "|Ψ⁺⟩", "expansion": "(|01⟩+|10⟩)/√2", "correlation": "Opposite"},
            {"name": "|Ψ⁻⟩", "expansion": "(|01⟩-|10⟩)/√2", "correlation": "Opposite"}
          ]
        }
      ]
    },
    "hardware": {
      "title": "Hardware Comparison",
      "description": "Comparison of leading qubit technologies",
      "comparison": [
        {
          "technology": "Superconducting",
          "companies": "IBM, Google, Rigetti",
          "gate_time": "20-50 ns",
          "T1": "~100 μs",
          "connectivity": "Limited (grid)",
          "fidelity": "99-99.5%"
        },
        {
          "technology": "Trapped Ion",
          "companies": "IonQ, Quantinuum",
          "gate_time": "10-200 μs",
          "T1": ">1 s",
          "connectivity": "All-to-all",
          "fidelity": "99.5-99.9%"
        },
        {
          "technology": "Photonic",
          "companies": "Xanadu, PsiQuantum",
          "gate_time": "~1 ns",
          "T1": "Long (photons)",
          "connectivity": "Flexible",
          "fidelity": "~99%"
        },
        {
          "technology": "Neutral Atom",
          "companies": "QuEra, Pasqal",
          "gate_time": "~1 μs",
          "T1": "~1 s",
          "connectivity": "Flexible (2D/3D)",
          "fidelity": "99-99.5%"
        }
      ]
    },
    "algorithms": {
      "title": "Algorithm Quick Reference",
      "groups": [
        {
          "id": "speedups",
          "title": "Quantum Speedups",
          "color": "#EF4444",
          "algorithms": [
            {"name": "Grover's Search", "classical": "O(N)", "quantum": "O(√N)", "speedup": "Quadratic"},
            {"name": "Shor's Factoring", "classical": "O(exp(N^1/3))", "quantum": "O((log N)³)", "speedup": "Exponential"},
            {"name": "Quantum Simulation", "classical": "O(exp(N))", "quantum": "O(poly(N))", "speedup": "Exponential"},
            {"name": "Quantum Phase Estimation", "classical": "varies", "quantum": "O(1/ε)", "speedup": "Exponential for eigenvalues"}
          ]
        }
      ]
    },
    "qiskit_snippets": {
      "title": "Qiskit Code Snippets",
      "groups": [
        {
          "id": "basics",
          "title": "Basic Operations",
          "color": "#10B981",
          "snippets": [
            {
              "name": "Create Circuit",
              "code": "from qiskit import QuantumCircuit\nqc = QuantumCircuit(2, 2)"
            },
            {
              "name": "Bell State",
              "code": "qc.h(0)\nqc.cx(0, 1)"
            },
            {
              "name": "Measure All",
              "code": "qc.measure_all()"
            },
            {
              "name": "Simulate",
              "code": "from qiskit_aer import AerSimulator\nsim = AerSimulator()\nresult = sim.run(qc).result()"
            }
          ]
        }
      ]
    }
  }
}

